{
  "asin": "B0CQ23GTZK",
  "title": "Paranix Spray Express 5 minutes - Lotion Spray Anti-Poux et Lentes 100% efficace : traite et protège – 100 ml – Peigne fin en métal inclus",
  "brand": "Paranix",
  "browse_classification": "Traitements anti-poux",
  "images": [
    {
      "variant": "MAIN",
      "url": "https://m.media-amazon.com/images/I/811HdLIiJlL.jpg",
      "width": 1973,
      "height": 2560
    },
    {
      "variant": "MAIN",
      "url": "https://m.media-amazon.com/images/I/41C9Pn0sK9L.jpg",
      "width": 385,
      "height": 500
    },
    {
      "variant": "MAIN",
      "url": "https://m.media-amazon.com/images/I/41C9Pn0sK9L._SL75_.jpg",
      "width": 58,
      "height": 75
    },
    {
      "variant": "PT01",
      "url": "https://m.media-amazon.com/images/I/71+icxdhm7L.jpg",
      "width": 1500,
      "height": 1500
    },
    {
      "variant": "PT01",
      "url": "https://m.media-amazon.com/images/I/512Bvw+QXKL.jpg",
      "width": 500,
      "height": 500
    },
    {
      "variant": "PT01",
      "url": "https://m.media-amazon.com/images/I/512Bvw+QXKL._SL75_.jpg",
      "width": 75,
      "height": 75
    },
    {
      "variant": "PT02",
      "url": "https://m.media-amazon.com/images/I/71gcQeYEo7L.jpg",
      "width": 1500,
      "height": 1500
    },
    {
      "variant": "PT02",
      "url": "https://m.media-amazon.com/images/I/51-W+F3O6GL.jpg",
      "width": 500,
      "height": 500
    },
    {
      "variant": "PT02",
      "url": "https://m.media-amazon.com/images/I/51-W+F3O6GL._SL75_.jpg",
      "width": 75,
      "height": 75
    },
    {
      "variant": "PT03",
      "url": "https://m.media-amazon.com/images/I/4178AX7jtcL.jpg",
      "width": 293,
      "height": 751
    },
    {
      "variant": "PT03",
      "url": "https://m.media-amazon.com/images/I/4178AX7jtcL._SL75_.jpg",
      "width": 29,
      "height": 75
    },
    {
      "variant": "PT04",
      "url": "https://m.media-amazon.com/images/I/5170dPQtQQL.jpg",
      "width": 268,
      "height": 802
    },
    {
      "variant": "PT04",
      "url": "https://m.media-amazon.com/images/I/5170dPQtQQL._SL75_.jpg",
      "width": 25,
      "height": 75
    },
    {
      "variant": "PT05",
      "url": "https://m.media-amazon.com/images/I/616tmgWfhOL.jpg",
      "width": 387,
      "height": 694
    },
    {
      "variant": "PT05",
      "url": "https://m.media-amazon.com/images/I/616tmgWfhOL._SL75_.jpg",
      "width": 42,
      "height": 75
    }
  ],
  "bullet_points": [
    "ACTION RAPIDE ET TRAITEMENT 100 % EFFICACE : Ce spray anti-poux élimine les poux en 5 min et les lentes en 10 min, Il protège contre les réinfestations pendant 72 heures grâce à sa technologie LPF",
    "SANS INSECTICIDE : Le spray Paranix EXPRESS 5 minutes est sans insecticide, son mode d’action est mécanique : les poux ne peuvent développer aucune résistance à l'un des ingrédients",
    "CONVIENT AUX ENFANTS DÈS 12 MOIS ET AUX ADULTES, Demander l'avis de votre médecin ou de votre pharmacien avant d'utiliser ce produit si vous êtes enceinte ou si vous allaitez",
    "FACILE À APPLIQUER ET RINCER : La formule du spray Paranix EXPRESS 5 minutes est sans silicone, Facile à appliquer et à rincer, les poux sont éliminés rapidement et en toute simplicité",
    "PEIGNE INCLUS : Le spray Paranix EXPRESS 5 minutes est un produit anti-poux équipé de son peigne en métal fin anti-poux pour retirer facilement les poux et lentes des cheveux"
  ],
  "description": "",
  "product_type": "HAIR_COMB"
}